opteryx_sqlalchemy-0.0.6.dist-info/licenses/LICENSE
sqlalchemy_dialect/__init__.py
sqlalchemy_dialect/dbapi.py
sqlalchemy_dialect/dialect.py
opteryx_sqlalchemy-0.0.6.dist-info/METADATA
opteryx_sqlalchemy-0.0.6.dist-info/WHEEL
opteryx_sqlalchemy-0.0.6.dist-info/entry_points.txt
opteryx_sqlalchemy-0.0.6.dist-info/top_level.txt
opteryx_sqlalchemy-0.0.6.dist-info/RECORD
