Metadata-Version: 2.4
Name: opteryx-sqlalchemy
Version: 0.0.6
Summary: Opteryx SQLAlchemy Dialect
Requires-Python: >=3.9
License-File: LICENSE
Requires-Dist: brotli-asgi>=1.6.0
Requires-Dist: python-jose[cryptography]>=3.3.0
Requires-Dist: cryptography>=46.0.3
Requires-Dist: requests>=2.32.5
Requires-Dist: python-multipart>=0.0.21
Requires-Dist: sqlalchemy>=2.0.45
Dynamic: license-file
